{
    "collections": {
        "lectures": {
            "schema": {
                "required_artifacts": [
                    "slides-eldridge.pdf",
                    "slides-wang.pdf",
                    "slides-wang.pptx"
                ],
                "optional_artifacts": [],
                "metadata_schema": {
                    "number": {
                        "type": "integer"
                    },
                    "date": {
                        "type": "smartdate"
                    },
                    "topic": {
                        "type": "string"
                    },
                    "reading": {
                        "type": "string"
                    },
                    "wang-recording": {
                        "type": "string",
                        "nullable": true
                    },
                    "wang-supplementary": {
                        "nullable": true,
                        "required": false,
                        "type": "dict",
                        "schema": {
                            "title": {
                                "type": "string"
                            },
                            "url": {
                                "type": "string"
                            }
                        }
                    },
                    "eldridge-videos": {
                        "type": "list",
                        "schema": {
                            "type": "dict",
                            "schema": {
                                "title": {
                                    "type": "string"
                                },
                                "url": {
                                    "type": "string"
                                }
                            }
                        }
                    }
                },
                "allow_unspecified_artifacts": false,
                "is_ordered": true
            },
            "publications": {
                "01-intro": {
                    "metadata": {
                        "date": "2021-01-05",
                        "number": 1,
                        "topic": "Introduction",
                        "reading": "Section 1.6",
                        "eldridge-videos": [
                            {
                                "title": "The Syllabus",
                                "url": "https://youtu.be/0VI7L7iwp8w"
                            },
                            {
                                "title": "Introduction",
                                "url": "https://youtu.be/g9YTOgkBfi0"
                            },
                            {
                                "title": "Example: Brute Force Clustering",
                                "url": "https://youtu.be/maG7rfv0Ugc"
                            },
                            {
                                "title": "Measuring Efficiency of Algorithms",
                                "url": "https://youtu.be/iiTLvdMHm_o"
                            },
                            {
                                "title": "Time Complexity Analysis",
                                "url": "https://youtu.be/9mCZfbpQqHg"
                            }
                        ],
                        "wang-recording": "https://youtu.be/8clPLa0XFKE"
                    },
                    "artifacts": {
                        "slides-eldridge.pdf": {
                            "path": "lectures/01-intro/slides-eldridge.pdf"
                        },
                        "slides-wang.pdf": {
                            "path": "lectures/01-intro/slides-wang.pdf"
                        },
                        "slides-wang.pptx": {
                            "path": "lectures/01-intro/slides-wang.pptx"
                        }
                    }
                },
                "02-time_complexity-pt_I": {
                    "metadata": {
                        "date": "2021-01-07",
                        "number": 2,
                        "topic": "Asymptotic Time Complexity, pt. I",
                        "reading": "Section 1.1 - 1.4",
                        "eldridge-videos": [
                            {
                                "title": "News",
                                "url": "https://youtu.be/5uHU0ySoNN8"
                            },
                            {
                                "title": "Nested Loops",
                                "url": "https://youtu.be/eUrLJ3Omjdo"
                            },
                            {
                                "title": "Linear and Quadratic",
                                "url": "https://youtu.be/cQac620u0jU"
                            },
                            {
                                "title": "Big Theta Notation",
                                "url": "https://youtu.be/Bck5PHtcvs8"
                            },
                            {
                                "title": "Big O and Big Omega",
                                "url": "https://youtu.be/SPFMl6GEjwI"
                            },
                            {
                                "title": "Limit Definitions",
                                "url": "https://youtu.be/y_O-Z2XpRmg"
                            }
                        ],
                        "wang-recording": "https://youtu.be/jefGive1PSA",
                        "wang-supplementary": {
                            "title": "More on Nested Loops",
                            "url": "https://youtu.be/44AILV3wYRA"
                        }
                    },
                    "artifacts": {
                        "slides-eldridge.pdf": {
                            "path": "lectures/02-time_complexity-pt_I/slides-eldridge.pdf"
                        },
                        "slides-wang.pdf": {
                            "path": "lectures/02-time_complexity-pt_I/slides-wang.pdf"
                        },
                        "slides-wang.pptx": {
                            "path": "lectures/02-time_complexity-pt_I/slides-wang.pptx"
                        }
                    }
                },
                "03-time_complexity-pt_II": {
                    "metadata": {
                        "date": "2021-01-12",
                        "number": 2,
                        "topic": "Asymptotic Time Complexity, pt. II",
                        "reading": "Section 1.5",
                        "eldridge-videos": [],
                        "wang-recording": null
                    },
                    "artifacts": {
                        "slides-eldridge.pdf": {
                            "path": "lectures/03-time_complexity-pt_II/slides-eldridge.pdf"
                        },
                        "slides-wang.pdf": {
                            "path": "lectures/03-time_complexity-pt_II/slides-wang.pdf"
                        },
                        "slides-wang.pptx": {
                            "path": "lectures/03-time_complexity-pt_II/slides-wang.pptx"
                        }
                    }
                }
            }
        },
        "discussions": {
            "schema": {
                "required_artifacts": [
                    "discussion.pdf",
                    "solution.pdf"
                ],
                "optional_artifacts": [],
                "metadata_schema": {
                    "number": {
                        "type": "integer"
                    },
                    "topic": {
                        "type": "string"
                    },
                    "date": {
                        "type": "smartdate"
                    },
                    "recording": {
                        "type": "string",
                        "required": false,
                        "nullable": true
                    }
                },
                "allow_unspecified_artifacts": false,
                "is_ordered": false
            },
            "publications": {
                "01-time_complexity": {
                    "metadata": {
                        "number": 1,
                        "topic": "Time Complexity Analysis",
                        "date": "2021-01-07",
                        "recording": "https://ucsd.zoom.us/rec/share/LLsxIlkvf5uiqbeUJOKmP6NwcCkmXZi2ke3brfgF9kJaGbRf3qpPl5oi9cnHtvPu.c139ypuUEn3MAuyn?startTime=1610067675000"
                    },
                    "artifacts": {
                        "discussion.pdf": {
                            "path": "discussions/01-time_complexity/discussion.pdf"
                        },
                        "solution.pdf": {
                            "path": "discussions/01-time_complexity/solution.pdf"
                        }
                    }
                }
            }
        },
        "homeworks": {
            "schema": {
                "required_artifacts": [
                    "homework.pdf",
                    "solution.pdf",
                    "template.zip"
                ],
                "optional_artifacts": [],
                "metadata_schema": {
                    "number": {
                        "type": "integer"
                    },
                    "topic": {
                        "type": "string"
                    },
                    "released": {
                        "type": "smartdatetime"
                    },
                    "due": {
                        "type": "smartdatetime"
                    }
                },
                "allow_unspecified_artifacts": false,
                "is_ordered": true
            },
            "publications": {
                "01-time_complexity": {
                    "metadata": {
                        "number": 1,
                        "topic": "Time Complexity Analysis",
                        "due": "2021-01-12 23:59:00",
                        "released": "2021-01-05 00:00:00"
                    },
                    "artifacts": {
                        "homework.pdf": {
                            "path": "homeworks/01-time_complexity/homework.pdf"
                        },
                        "template.zip": {
                            "path": "homeworks/01-time_complexity/template.zip"
                        }
                    }
                }
            }
        },
        "default": {
            "schema": {
                "required_artifacts": [],
                "optional_artifacts": null,
                "metadata_schema": null,
                "allow_unspecified_artifacts": true,
                "is_ordered": false
            },
            "publications": {
                "notes": {
                    "metadata": {},
                    "artifacts": {
                        "book.pdf": {
                            "path": "default/notes/book.pdf"
                        }
                    }
                }
            }
        }
    }
}